mzml2gnps/__init__.py
mzml2gnps/command_line.py
mzml2gnps/main.py
mzml2gnps/methods.py
mzml2gnps/test.py
mzml2gnps-1.0.3.dist-info/LICENSE
mzml2gnps-1.0.3.dist-info/METADATA
mzml2gnps-1.0.3.dist-info/WHEEL
mzml2gnps-1.0.3.dist-info/entry_points.txt
mzml2gnps-1.0.3.dist-info/top_level.txt
mzml2gnps-1.0.3.dist-info/RECORD
