Metadata-Version: 2.1
Name: mzml2gnps
Version: 1.0.3
Summary: A package for preprocessing mzML files for GNPS molecular networking
Author-email: YunyingXie <xieyy@imb.pumc.edu.cn>
License: MIT
Project-URL: homepage, https://github.com/xieyying/mzml2gnps
Classifier: Development Status :: 3 - Alpha
Classifier: Intended Audience :: Science/Research
Classifier: Topic :: Scientific/Engineering :: Bio-Informatics
Classifier: License :: OSI Approved :: MIT License
Classifier: Programming Language :: Python :: 3
Classifier: Programming Language :: Python :: 3.8
Classifier: Programming Language :: Python :: 3.9
Classifier: Programming Language :: Python :: 3.10
License-File: LICENSE
Requires-Dist: pandas==2.0.3
Requires-Dist: numpy<2.0.0,>=1.22.0
Requires-Dist: pyopenms==3.1.0
